redditquery/__init__.py
redditquery/__main__.py
redditquery/database.py
redditquery/index.py
redditquery/parse.py
redditquery/reddit.py
redditquery/utils.py
redditquery-0.1.0.dist-info/DESCRIPTION.rst
redditquery-0.1.0.dist-info/METADATA
redditquery-0.1.0.dist-info/RECORD
redditquery-0.1.0.dist-info/WHEEL
redditquery-0.1.0.dist-info/entry_points.txt
redditquery-0.1.0.dist-info/metadata.json
redditquery-0.1.0.dist-info/top_level.txt
