Metadata-Version: 2.0
Name: redditquery
Version: 0.1.0
Summary: An offline information retrieval system for full-text search on reddit comments.
Home-page: https://github.com/kuchenrolle/redditquery
Author: Christian Adam
Author-email: kuchenrolle@googlemail.com
License: MIT
Keywords: reddit,inverted index,search
Platform: UNKNOWN
Classifier: Development Status :: 5 - Production/Stable
Classifier: Intended Audience :: Developers
Classifier: License :: OSI Approved :: BSD License
Classifier: Operating System :: Unix
Classifier: Operating System :: POSIX
Classifier: Operating System :: Microsoft :: Windows
Classifier: Programming Language :: Python :: 3
Classifier: Programming Language :: Python :: 3.1
Classifier: Programming Language :: Python :: 3.2
Classifier: Programming Language :: Python :: 3.3
Classifier: Programming Language :: Python :: 3.4
Classifier: Programming Language :: Python :: 3.5
Classifier: Programming Language :: Python :: 3.6
Classifier: Topic :: Utilities
Requires-Dist: pandas
Requires-Dist: spacy
